fybrik_python_vault/__init__.py
fybrik_python_vault-0.2.0.dist-info/METADATA
fybrik_python_vault-0.2.0.dist-info/WHEEL
fybrik_python_vault-0.2.0.dist-info/top_level.txt
fybrik_python_vault-0.2.0.dist-info/RECORD
