Metadata-Version: 2.1
Name: fybrik-python-vault
Version: 0.2.0
Summary: Python Vault Package for Fybrik Components
Home-page: https://github.com/fybrik/fybrik/tree/master/python/vault
Author: FybrikUser
Author-email: FybrikUser@il.ibm.com
License: Apache License, Version 2.0
Requires-Dist: fybrik-python-logging
Requires-Dist: fybrik-python-tls
Requires-Dist: requests
